README.md
setup.py
ci3/__init__.py
ci3/cli.py
ci3/error.py
ci3/log.py
ci3/version.py
ci3/commands/__init__.py
ci3/commands/base.py
ci3/commands/dkr.py
ci3/commands/dotci3.py
ci3/commands/gke.py
ci3/commands/k8s.py
kubic_ci.egg-info/PKG-INFO
kubic_ci.egg-info/SOURCES.txt
kubic_ci.egg-info/dependency_links.txt
kubic_ci.egg-info/entry_points.txt
kubic_ci.egg-info/requires.txt
kubic_ci.egg-info/top_level.txt