Metadata-Version: 1.1
Name: kubic-ci
Version: 0.1.4
Summary: continuous integration for kubernetes
Home-page: https://github.com/kubic-ci/ci3
Author: Kubic CI
Author-email: eugeny.yakimovitch@gmail.com
License: MIT
Keywords: kubernetes git ci continuous integration
Platform: UNKNOWN
Classifier: Development Status :: 3 - Alpha
Classifier: Intended Audience :: Developers
Classifier: Topic :: Software Development :: Build Tools
Classifier: License :: OSI Approved :: MIT License
Classifier: Programming Language :: Python :: 2
Classifier: Programming Language :: Python :: 2.7
Classifier: Programming Language :: Python :: 3
Classifier: Programming Language :: Python :: 3.3
Classifier: Programming Language :: Python :: 3.4
Classifier: Programming Language :: Python :: 3.5
